pykitopen/__init__.py
pykitopen/cli.py
pykitopen/config.py
pykitopen/kitopen.py
pykitopen/mixins.py
pykitopen/publication.py
pykitopen/pykitopen.py
pykitopen/search.py
pykitopen/util.py
pykitopen-0.1.1.dist-info/AUTHORS.rst
pykitopen-0.1.1.dist-info/LICENSE
pykitopen-0.1.1.dist-info/METADATA
pykitopen-0.1.1.dist-info/WHEEL
pykitopen-0.1.1.dist-info/entry_points.txt
pykitopen-0.1.1.dist-info/top_level.txt
pykitopen-0.1.1.dist-info/RECORD
