Metadata-Version: 2.1
Name: pykitopen
Version: 0.1.1
Summary: A KITOpen wrapper for python
Home-page: https://github.com/the16thpythonist/pykitopen
Author: Jonas Teufel
Author-email: jonseb1998@gmail.com
License: MIT license
Keywords: pykitopen
Platform: UNKNOWN
Classifier: Development Status :: 2 - Pre-Alpha
Classifier: Intended Audience :: Developers
Classifier: License :: OSI Approved :: MIT License
Classifier: Natural Language :: English
Classifier: Programming Language :: Python :: 3
Classifier: Programming Language :: Python :: 3.5
Classifier: Programming Language :: Python :: 3.6
Classifier: Programming Language :: Python :: 3.7
Classifier: Programming Language :: Python :: 3.8
Requires-Python: >=3.5
Requires-Dist: Click (>=7.0)
Requires-Dist: requests
